etc_jupyterlab_distribution/__init__.py
etc_jupyterlab_distribution/_frontend.py
etc_jupyterlab_distribution/_version.py
etc_jupyterlab_distribution/widget.py
etc_jupyterlab_distribution/labextension/build_log.json
etc_jupyterlab_distribution/labextension/package.json
etc_jupyterlab_distribution/labextension/static/lib_index_js.f135dec82444fd3e5957.js
etc_jupyterlab_distribution/labextension/static/lib_index_js.f135dec82444fd3e5957.js.map
etc_jupyterlab_distribution/labextension/static/lib_plugin_js.9fcdd0fbfcd9779fdd28.js
etc_jupyterlab_distribution/labextension/static/lib_plugin_js.9fcdd0fbfcd9779fdd28.js.map
etc_jupyterlab_distribution/labextension/static/lib_widget_js.9766f24e56ee53f9c2ce.js
etc_jupyterlab_distribution/labextension/static/lib_widget_js.9766f24e56ee53f9c2ce.js.map
etc_jupyterlab_distribution/labextension/static/lib_widget_js.ba0d6e681d5bcd3a8318.js
etc_jupyterlab_distribution/labextension/static/lib_widget_js.ba0d6e681d5bcd3a8318.js.map
etc_jupyterlab_distribution/labextension/static/node_modules_educational-technology-collective_etc_smartboard_dist_index_js.751eb7fc32a28e79664b.js
etc_jupyterlab_distribution/labextension/static/node_modules_educational-technology-collective_etc_smartboard_dist_index_js.751eb7fc32a28e79664b.js.map
etc_jupyterlab_distribution/labextension/static/remoteEntry.5fd712105a034fd8ba42.js
etc_jupyterlab_distribution/labextension/static/remoteEntry.5fd712105a034fd8ba42.js.map
etc_jupyterlab_distribution/labextension/static/remoteEntry.a3401e3fda4d3d396176.js
etc_jupyterlab_distribution/labextension/static/remoteEntry.a3401e3fda4d3d396176.js.map
etc_jupyterlab_distribution/labextension/static/style.js
etc_jupyterlab_distribution/nbextension/extension.js
etc_jupyterlab_distribution/nbextension/index.js
etc_jupyterlab_distribution/nbextension/index.js.map
etc_jupyterlab_distribution/tests/__init__.py
etc_jupyterlab_distribution/tests/conftest.py
etc_jupyterlab_distribution/tests/test_example.py
etc_jupyterlab_distribution-0.1.2.dist-info/LICENSE.txt
etc_jupyterlab_distribution-0.1.2.dist-info/METADATA
etc_jupyterlab_distribution-0.1.2.dist-info/WHEEL
etc_jupyterlab_distribution-0.1.2.dist-info/top_level.txt
etc_jupyterlab_distribution-0.1.2.dist-info/RECORD
